CHANGES.rst
MANIFEST.in
README.rst
setup.py
collective/__init__.py
collective.carousel.egg-info/PKG-INFO
collective.carousel.egg-info/SOURCES.txt
collective.carousel.egg-info/dependency_links.txt
collective.carousel.egg-info/entry_points.txt
collective.carousel.egg-info/namespace_packages.txt
collective.carousel.egg-info/not-zip-safe
collective.carousel.egg-info/requires.txt
collective.carousel.egg-info/top_level.txt
collective/carousel/__init__.py
collective/carousel/configure.zcml
collective/carousel/interfaces.py
collective/carousel/schemaextender.py
collective/carousel/testing.py
collective/carousel/testing.zcml
collective/carousel/vocabularies.py
collective/carousel/browser/__init__.py
collective/carousel/browser/configure.zcml
collective/carousel/browser/leadimagetile.py
collective/carousel/browser/viewlets.py
collective/carousel/browser/resources/carousel.css
collective/carousel/browser/resources/carousel.js
collective/carousel/browser/templates/banner_tile.pt
collective/carousel/browser/templates/carousel.pt
collective/carousel/browser/templates/default_tile.pt
collective/carousel/browser/templates/image_tile.pt
collective/carousel/browser/templates/lead_image_tile.pt
collective/carousel/browser/templates/news_item_tile.pt
collective/carousel/locales/collective.carousel.pot
collective/carousel/locales/cs/LC_MESSAGES/collective.carousel.mo
collective/carousel/locales/cs/LC_MESSAGES/collective.carousel.po
collective/carousel/locales/da/LC_MESSAGES/collective.carousel.mo
collective/carousel/locales/da/LC_MESSAGES/collective.carousel.po
collective/carousel/locales/es/LC_MESSAGES/collective.carousel.mo
collective/carousel/locales/es/LC_MESSAGES/collective.carousel.po
collective/carousel/locales/fr/LC_MESSAGES/collective.carousel.mo
collective/carousel/locales/fr/LC_MESSAGES/collective.carousel.po
collective/carousel/locales/no/LC_MESSAGES/collective.carousel.mo
collective/carousel/locales/no/LC_MESSAGES/collective.carousel.po
collective/carousel/locales/pt-br/LC_MESSAGES/collective.carousel.mo
collective/carousel/locales/pt-br/LC_MESSAGES/collective.carousel.po
collective/carousel/locales/ru/LC_MESSAGES/collective.carousel.mo
collective/carousel/locales/ru/LC_MESSAGES/collective.carousel.po
collective/carousel/portlets/__init__.py
collective/carousel/portlets/carousel.pt
