Metadata-Version: 1.1
Name: collective.carousel
Version: 1.7
Summary: Add-on for having Collections' results presented as a nice carousel
Home-page: https://github.com/collective/collective.carousel
Author: Jarn [Denys Mishunov]
Author-email: info@jarn.com
License: GPL
Keywords: plone zope collection carousel
Platform: UNKNOWN
Classifier: Framework :: Plone
Classifier: Programming Language :: Python
Classifier: Topic :: Software Development :: Libraries :: Python Modules
